krpy/__init__.py
krpy/kr.py
krpy-0.1.2.dist-info/LICENSE
krpy-0.1.2.dist-info/WHEEL
krpy-0.1.2.dist-info/METADATA
krpy-0.1.2.dist-info/RECORD
