Metadata-Version: 2.1
Name: krpy
Version: 0.1.2
Summary: Relative Permeabilities Utility Tool
License: MIT
Author: Santiago Cuervo
Author-email: scuervo91@gmail.com
Requires-Python: >=3.7.1,<3.11
Classifier: License :: OSI Approved :: MIT License
Classifier: Programming Language :: Python :: 3
Classifier: Programming Language :: Python :: 3.8
Classifier: Programming Language :: Python :: 3.9
Classifier: Programming Language :: Python :: 3.10
Requires-Dist: matplotlib (>=3.4.3,<4.0.0)
Requires-Dist: numpy (>=1.21.4,<2.0.0)
Requires-Dist: pandas (>=1.3.4,<2.0.0)
Requires-Dist: pydantic (>=1.8.2,<2.0.0)
Requires-Dist: scipy (>=1.7.2,<2.0.0)
Requires-Dist: seaborn (>=0.11.2,<0.12.0)
